powerline_tailscale/__init__.py
powerline_tailscale/segments.py
powerline_tailscale-1.0.2.dist-info/LICENSE
powerline_tailscale-1.0.2.dist-info/METADATA
powerline_tailscale-1.0.2.dist-info/WHEEL
powerline_tailscale-1.0.2.dist-info/top_level.txt
powerline_tailscale-1.0.2.dist-info/RECORD
