Metadata-Version: 2.1
Name: powerline-tailscale
Version: 1.0.2
Summary: A Powerline segment for showing the status of Tailscale
Author: Üllar Seerme
License: MIT
Project-URL: Homepage, https://github.com/usrme/powerline-tailscale
Project-URL: Documentation, https://github.com/usrme/powerline-tailscale
Project-URL: Repository, https://github.com/usrme/powerline-tailscale
Keywords: powerline,tailscale
Classifier: Development Status :: 5 - Production/Stable
Classifier: Environment :: Console
Classifier: Intended Audience :: Developers
Classifier: License :: OSI Approved :: MIT License
Classifier: Topic :: Terminals
Classifier: Programming Language :: Python :: 3 :: Only
Classifier: Programming Language :: Python :: 3.9
Classifier: Programming Language :: Python :: 3.10
Classifier: Programming Language :: Python :: 3.11
Requires-Python: >=3.9
License-File: LICENSE
